dev.py
intel.py
niger-0.0.2.dist-info/METADATA
niger-0.0.2.dist-info/WHEEL
niger-0.0.2.dist-info/top_level.txt
niger-0.0.2.dist-info/RECORD
