Metadata-Version: 2.1
Name: niger
Version: 0.0.2
Summary: so susy
Author: susy baka
Classifier: Programming Language :: Python :: 3
Classifier: License :: OSI Approved :: MIT License
Classifier: Operating System :: OS Independent
Requires-Python: >=3.6
